README.txt
setup.py
pchip/__init__.py
pchip/pchip.py
pchip.egg-info/PKG-INFO
pchip.egg-info/SOURCES.txt
pchip.egg-info/dependency_links.txt
pchip.egg-info/top_level.txt