Metadata-Version: 1.1
Name: pchip
Version: 0.0.1
Summary: Python script to notify availability of domain names
Home-page: https://github.com/hech/domain-check/
Author: Tricia Hinkson
Author-email: trhinkson@gmail.com
License: UNKNOWN
Keywords: domain,cli,website
Platform: UNKNOWN
Classifier: Programming Language :: Python
Classifier: Development Status :: 2 - Pre-Alpha
Classifier: Environment :: Other Environment
Classifier: Intended Audience :: Developers
Classifier: License :: OSI Approved :: GNU General Public License v2 (GPLv2)
Classifier: Operating System :: OS Independent
Classifier: Topic :: Utilities
